COPYRIGHT.txt
LICENSE_GPLv3.txt
MANIFEST.in
README.rst
setup.cfg
setup.py
gskrawler/__init__.py
gskrawler.egg-info/PKG-INFO
gskrawler.egg-info/SOURCES.txt
gskrawler.egg-info/dependency_links.txt
gskrawler.egg-info/requires.txt
gskrawler.egg-info/top_level.txt