Metadata-Version: 1.1
Name: gskrawler
Version: 1.0.0
Summary: gskrawler will enter your domain and scan every page of your website, extracting page titles, descriptions, keywords, and links etc..
Home-page: https://github.com/username/
Author: Siva Avis
Author-email: forhacku@gmail.com
License: UNKNOWN
Keywords: gskrawler scraping website emails data webcrawler
Platform: UNKNOWN
Classifier: Intended Audience :: Developers
Classifier: Topic :: Communications
Classifier: Topic :: Software Development :: Libraries
Classifier: License :: OSI Approved :: GNU General Public License v3 or later (GPLv3+)
Classifier: Programming Language :: Python :: 3
